aviatrix_migration_nat-0.17.0.dist-info/RECORD
aviatrix_migration_nat-0.17.0.dist-info/WHEEL
aviatrix_migration_nat-0.17.0.dist-info/entry_points.txt
aviatrix_migration_nat-0.17.0.dist-info/top_level.txt
aviatrix_migration_nat-0.17.0.dist-info/METADATA
naterminator/naterminator.cpython-310-darwin.so
naterminator/rollback.cpython-310-darwin.so
naterminator/__init__.cpython-310-darwin.so
naterminator/core/config.py
naterminator/core/ConfigAdaptor.cpython-310-darwin.so
naterminator/core/config_vpc_migration.py
naterminator/core/AppExitStatus.cpython-310-darwin.so
naterminator/core/logconf.cpython-310-darwin.so
naterminator/core/exceptions.cpython-310-darwin.so
naterminator/core/Globals.cpython-310-darwin.so
naterminator/core/__init__.cpython-310-darwin.so
naterminator/core/config_gateway_size_table.cpython-310-darwin.so
naterminator/core/ErrorStatusHandler.cpython-310-darwin.so
naterminator/core/BackupDescriptor.cpython-310-darwin.so
naterminator/core/ConfigAdaptorVpcMigration.cpython-310-darwin.so
naterminator/lib/spoke.cpython-310-darwin.so
naterminator/lib/avx_account.cpython-310-darwin.so
naterminator/lib/gateway_size.cpython-310-darwin.so
naterminator/lib/commonlib.cpython-310-darwin.so
naterminator/lib/exception.cpython-310-darwin.so
naterminator/lib/route_table.cpython-310-darwin.so
naterminator/lib/aws_cred.cpython-310-darwin.so
naterminator/lib/__init__.cpython-310-darwin.so
naterminator/lib/test.cpython-310-darwin.so
naterminator/lib/aviatrix_backend.cpython-310-darwin.so
naterminator/lib/s3.cpython-310-darwin.so
naterminator/lib/save_state.cpython-310-darwin.so
naterminator/lib/aws.cpython-310-darwin.so
naterminator/lib/ip.cpython-310-darwin.so
naterminator/lib/natgw.cpython-310-darwin.so
naterminator/lib/route_table_az_affinity/route_table_clone.cpython-310-darwin.so
naterminator/lib/route_table_az_affinity/routetable.cpython-310-darwin.so
naterminator/lib/route_table_az_affinity/SubnetAzInfo.cpython-310-darwin.so
naterminator/lib/route_table_az_affinity/route.cpython-310-darwin.so
naterminator/lib/route_table_az_affinity/__init__.cpython-310-darwin.so
naterminator/lib/route_table_az_affinity/routetables.cpython-310-darwin.so
