Metadata-Version: 2.1
Name: aviatrix-migration-nat
Version: 0.17.0
Requires-Dist: boto3==1.24.22
Requires-Dist: botocore==1.27.22
Requires-Dist: certifi==2020.12.5
Requires-Dist: chardet==4.0.0
Requires-Dist: decorator==5.0.9
Requires-Dist: idna==2.10
Requires-Dist: Jinja2==3.0.3
Requires-Dist: jmespath==0.10.0
Requires-Dist: py==1.10.0
Requires-Dist: pydantic==1.9.0
Requires-Dist: python-dateutil==2.8.1
Requires-Dist: PyYAML==6.0.2
Requires-Dist: requests==2.25.1
Requires-Dist: retry==0.9.2
Requires-Dist: s3transfer==0.6.0
Requires-Dist: six==1.16.0
Requires-Dist: typing-extensions==4.5.0
Requires-Dist: urllib3==1.26.4
Requires-Dist: packaging==21.3
